Metadata-Version: 1.0
Name: generate-cmake
Version: 1.8.1
Summary: Python Super CMake
Home-page: https://github.com/jpanikulam/experiments/tree/master/pymake
Author: Jacob Panikulam
Author-email: jpanikul@gmail.com
License: MIT
Keywords: cmake make stupid
Platform: any
